cria_index/core/__init__.py
cria_index/core/llama_packs/__init__.py
cria_index/core/llama_packs/base.py
cria_index/core/llms/__init__.py
cria_index/core/llms/base.py
cria_index/core/readers/__init__.py
cria_index/core/readers/base.py
cria_index/core/tools/__init__.py
cria_index/core/tools/base.py
cria_index/core/vector_stores/__init__.py
cria_index/core/vector_stores/base.py
cria_core-0.1.1.dist-info/METADATA
cria_core-0.1.1.dist-info/WHEEL
cria_core-0.1.1.dist-info/RECORD
